[
    {
      "constant": true,
      "inputs": [],
      "name": "payer",
      "outputs": [
        {
          "name": "",
          "type": "address"
        }
      ],
      "payable": false,
      "stateMutability": "view",
      "type": "function"
    },
    {
      "constant": true,
      "inputs": [
        {
          "name": "",
          "type": "address"
        },
        {
          "name": "",
          "type": "address"
        },
        {
          "name": "",
          "type": "bytes32"
        }
      ],
      "name": "deployed",
      "outputs": [
        {
          "name": "",
          "type": "bool"
        }
      ],
      "payable": false,
      "stateMutability": "view",
      "type": "function"
    },
    {
      "constant": true,
      "inputs": [],
      "name": "supplier",
      "outputs": [
        {
          "name": "",
          "type": "address"
        }
      ],
      "payable": false,
      "stateMutability": "view",
      "type": "function"
    },
    {
      "constant": true,
      "inputs": [],
      "name": "controller",
      "outputs": [
        {
          "name": "",
          "type": "address"
        }
      ],
      "payable": false,
      "stateMutability": "view",
      "type": "function"
    },
    {
      "inputs": [
        {
          "name": "_controllerAddress",
          "type": "address"
        }
      ],
      "payable": false,
      "stateMutability": "nonpayable",
      "type": "constructor"
    },
    {
      "anonymous": false,
      "inputs": [
        {
          "indexed": true,
          "name": "token",
          "type": "address"
        },
        {
          "indexed": true,
          "name": "packable",
          "type": "address"
        },
        {
          "indexed": false,
          "name": "packableId",
          "type": "bytes32"
        },
        {
          "indexed": true,
          "name": "deployed",
          "type": "address"
        }
      ],
      "name": "Deploy",
      "type": "event"
    },
    {
      "constant": false,
      "inputs": [
        {
          "name": "_token",
          "type": "address"
        },
        {
          "name": "_packable",
          "type": "address"
        },
        {
          "name": "_packableId",
          "type": "bytes32"
        }
      ],
      "name": "deploy",
      "outputs": [],
      "payable": false,
      "stateMutability": "nonpayable",
      "type": "function"
    }
  ]